optimodel_server/OptimodelError.py
optimodel_server/__init__.py
optimodel_server/cli.py
optimodel_server/index.py
optimodel_server/optimodel-server-config.json
optimodel_server/Config/Config.py
optimodel_server/Config/__init__.py
optimodel_server/Config/types.py
optimodel_server/GuardClient/__init__.py
optimodel_server/GuardClient/guardClient.py
optimodel_server/GuardClient/guardClientEncoder.py
optimodel_server/Planner/Planner.py
optimodel_server/Planner/__init__.py
optimodel_server/Providers/AnthropicProvider.py
optimodel_server/Providers/BaseProviderClass.py
optimodel_server/Providers/BedrockProvider.py
optimodel_server/Providers/CommonUtils.py
optimodel_server/Providers/GeminiProvider.py
optimodel_server/Providers/GroqProvider.py
optimodel_server/Providers/MistralAIProvider.py
optimodel_server/Providers/MistralCodestralProvider.py
optimodel_server/Providers/OpenAIProvider.py
optimodel_server/Providers/TogetherProvider.py
optimodel_server/Providers/__init__.py
optimodel_server/Routes/__init__.py
optimodel_server/Routes/Proxy/AnthropicProxy.py
optimodel_server/Routes/Proxy/GeminiProxy.py
optimodel_server/Routes/Proxy/GroqProxy.py
optimodel_server/Routes/Proxy/OpenAIProxy.py
optimodel_server/Utils/QueryModelMain.py
optimodel_server-1.20.0.dist-info/METADATA
optimodel_server-1.20.0.dist-info/WHEEL
optimodel_server-1.20.0.dist-info/entry_points.txt
optimodel_server-1.20.0.dist-info/top_level.txt
optimodel_server-1.20.0.dist-info/RECORD
