Metadata-Version: 2.1
Name: optimodel-server
Version: 1.20.0
Summary: A smart framework for calling models in the most efficient way possible
Author-email: Lytix <support@lytix.com>
Project-URL: Homepage, https://github.com/Lytix-Labs/optimodel
Project-URL: Issues, https://github.com/Lytix-Labs/optimodel/issues
Classifier: Programming Language :: Python :: 3
Classifier: License :: OSI Approved :: MIT License
Classifier: Operating System :: OS Independent
Requires-Python: >=3.8
Requires-Dist: requests==2.31.0
Requires-Dist: urllib3==2.2.1
Requires-Dist: fastapi==0.111.0
Requires-Dist: together===1.2.1
Requires-Dist: boto3==1.34.131
Requires-Dist: uvicorn==0.30.1
Requires-Dist: openai==1.45.0
Requires-Dist: groq==0.9.0
Requires-Dist: anthropic==0.31.2
Requires-Dist: mistralai==1.0.2
Requires-Dist: google-generativeai==0.7.2
Requires-Dist: brotli==1.1.0
Requires-Dist: optimodel-types==0.3.0
